<World>
    <enemies>
    <enemy id="unknown">
        <lvl id="1" HP="30" MP="0" def="3" mob="8" str="4"/>
        <lvl id="2" HP="33" MP="0" def="4" mob="8" str="4"/>
        <lvl id="3" HP="36" MP="0" def="5" mob="8" str="4"/>
    </enemy>
    <enemy id="soldier">
        <lvl id="1" HP="15" MP="0" def="2" mob="8" str="2"/>
        <lvl id="2" HP="18" MP="0" def="2" mob="8" str="2"/>
        <lvl id="3" HP="21" MP="0" def="3" mob="8" str="3"/>
    </enemy>
    <enemy id="reese">
        <lvl id="5" HP="35" MP="3" def="5" mob="3" str="6"/>
    </enemy>
    </enemies>

    <area id="1">
        <enemy id="unknown" lvl="1" x="17" y="4" />
        <enemy id="soldier" lvl="1" x="16" y="4" />
        <enemy id="soldier" lvl="1" x="18" y="4" />
    </area>

    <area id="2">
        <enemy id="reese" lvl="5" x="7" y="7" />
        <enemy id="soldier" lvl="2" x="6" y="7" />
        <enemy id="soldier" lvl="3" x="7" y="6" />
        <enemy id="soldier" lvl="3" x="8" y="7" />
    </area>

    <area id="test">
        <enemy id="soldier" lvl="1" x="4" y="6" />
    </area>
</World>
